fm22x/__init__.py
fm22x/connection.py
fm22x/note.py
fm22x/request.py
fm22x/response.py
fm22x/type.py
fm22x-0.0.1.dist-info/METADATA
fm22x-0.0.1.dist-info/WHEEL
fm22x-0.0.1.dist-info/top_level.txt
fm22x-0.0.1.dist-info/RECORD
