Metadata-Version: 2.1
Name: fm22x
Version: 0.0.1
Summary: fm22x sdk for python in sansio style
Home-page: https://github.com/synodriver/fm22x
Author: synodriver
Author-email: diguohuangjiajinweijun@gmail.com
Maintainer: synodriver
License: GPLv3
Keywords: sansio,fm22x
Classifier: Development Status :: 3 - Alpha
Classifier: Framework :: AsyncIO
Classifier: Operating System :: OS Independent
Classifier: License :: OSI Approved :: GNU General Public License v3 (GPLv3)
Classifier: Programming Language :: Python
Classifier: Programming Language :: Python :: 3.8
Classifier: Programming Language :: Python :: 3.9
Classifier: Programming Language :: Python :: 3.10
Classifier: Programming Language :: Python :: 3.11
Classifier: Programming Language :: Python :: 3.12
Classifier: Programming Language :: Python :: 3.13
Classifier: Programming Language :: Python :: Implementation :: CPython
Classifier: Programming Language :: Python :: Implementation :: PyPy
Requires-Python: >=3.8
